MANIFEST.in
README.rst
setup.cfg
setup.py
boxhed_kernel/CMakeLists.txt
boxhed_kernel/LICENSE
boxhed_kernel/VERSION
boxhed_kernel/__init__.py
boxhed_kernel/callback.py
boxhed_kernel/compat.py
boxhed_kernel/core.py
boxhed_kernel/dask.py
boxhed_kernel/data.py
boxhed_kernel/libpath.py
boxhed_kernel/plotting.py
boxhed_kernel/rabit.py
boxhed_kernel/sklearn.py
boxhed_kernel/tracker.py
boxhed_kernel/training.py
boxhed_kernel.egg-info/PKG-INFO
boxhed_kernel.egg-info/SOURCES.txt
boxhed_kernel.egg-info/dependency_links.txt
boxhed_kernel.egg-info/not-zip-safe
boxhed_kernel.egg-info/requires.txt
boxhed_kernel.egg-info/top_level.txt
boxhed_kernel/cmake/Doc.cmake
boxhed_kernel/cmake/FindPrefetchIntrinsics.cmake
boxhed_kernel/cmake/Python_version.in
boxhed_kernel/cmake/RPackageInstall.cmake.in
boxhed_kernel/cmake/RPackageInstallTargetSetup.cmake
boxhed_kernel/cmake/Sanitizer.cmake
boxhed_kernel/cmake/Utils.cmake
boxhed_kernel/cmake/Version.cmake
boxhed_kernel/cmake/boxhed_kernel-config.cmake.in
boxhed_kernel/cmake/boxhed_kernel.pc.in
boxhed_kernel/cmake/version_config.h.in
boxhed_kernel/cmake/modules/FindASan.cmake
boxhed_kernel/cmake/modules/FindLSan.cmake
boxhed_kernel/cmake/modules/FindLibR.cmake
boxhed_kernel/cmake/modules/FindNVML.cmake
boxhed_kernel/cmake/modules/FindNVTX.cmake
boxhed_kernel/cmake/modules/FindNccl.cmake
boxhed_kernel/cmake/modules/FindTSan.cmake
boxhed_kernel/cmake/modules/FindUBSan.cmake
boxhed_kernel/dmlc-core/.editorconfig
boxhed_kernel/dmlc-core/CMakeLists.txt
boxhed_kernel/dmlc-core/LICENSE
boxhed_kernel/dmlc-core/Makefile
boxhed_kernel/dmlc-core/README.md
boxhed_kernel/dmlc-core/appveyor.yml
boxhed_kernel/dmlc-core/cmake/Sanitizer.cmake
boxhed_kernel/dmlc-core/cmake/Utils.cmake
boxhed_kernel/dmlc-core/cmake/build_config.h.in
boxhed_kernel/dmlc-core/cmake/dmlc-config.cmake.in
boxhed_kernel/dmlc-core/cmake/gtest_cmake.in
boxhed_kernel/dmlc-core/cmake/lint.cmake
boxhed_kernel/dmlc-core/cmake/Modules/FindASan.cmake
boxhed_kernel/dmlc-core/cmake/Modules/FindHDFS.cmake
boxhed_kernel/dmlc-core/cmake/Modules/FindLSan.cmake
boxhed_kernel/dmlc-core/cmake/Modules/FindTSan.cmake
boxhed_kernel/dmlc-core/cmake/Modules/FindUBSan.cmake
boxhed_kernel/dmlc-core/doc/.gitignore
