Metadata-Version: 2.1
Name: boxhed-kernel
Version: 2.0.2
Summary: XGBoost Python Package
Home-page: https://github.com/dmlc/boxhed_kernel
License: Apache-2.0
Platform: UNKNOWN
Classifier: License :: OSI Approved :: Apache Software License
Classifier: Development Status :: 5 - Production/Stable
Classifier: Operating System :: OS Independent
Classifier: Programming Language :: Python
Classifier: Programming Language :: Python :: 3
Classifier: Programming Language :: Python :: 3.6
Classifier: Programming Language :: Python :: 3.7
Classifier: Programming Language :: Python :: 3.8
Requires-Python: >=3.6
Provides-Extra: pandas
Provides-Extra: scikit-learn
Provides-Extra: dask
Provides-Extra: datatable
Provides-Extra: plotting
